{
  "id": "mock-doc-id",
  "url": null,
  "type": "blogpost",
  "href": null,
  "tags": [],
  "first_publication_date": "1970-01-01T00:00:01+0000",
  "last_publication_date": "1970-01-01T00:00:01+0000",
  "slugs": [],
  "linked_documents": [],
  "lang": "en-us",
  "alternate_languages": [],
  "data": {
    "title": "worried",
    "author": "wrapped",
    "publicationdate": "2016-08-02",
    "description": [
      {
        "type": "paragraph",
        "text": "Exercitation laboris quis commodo in qui excepteur anim laborum laborum esse ipsum irure. Pariatur in id anim tempor ad dolor culpa esse eu veniam ad aliquip irure. Non ea amet eu do excepteur.",
        "spans": []
      }
    ],
    "slices": []
  }
}